{"5LO6jOIySx/yPz5w8ygO9w==":"background1.jpg","7lhu0OkjmShqxKC8lgIjjw==":"background2.jpg","VljI7Sx4fCR63syy/rpqnQ==":"face2.jpg","OLZ9YoOfFKVqh2XUYy73QQ==":"face3.jpg","oPlK96J4CLs6i6eK0xZFRQ==":"01.jpg","+owzpdRy7bspdMcUQZBcsg==":"02.jpg","fbj5x6J0YfB/UqYQBQ1Qbg==":"05.jpg","xeDjZpOprNc//jn/MrG1+w==":"03.jpg","YiA1UDN/EMEa4f1QaiRHZg==":"04.jpg","MI6m1kyworYgDftElslMHw==":"face1.jpg","GN2ohhu53/HZnv+ETfNgSg==":"mbr-120x120.png","pVmUPaTq4sGkYFE0jgeVpg==":"background1.jpeg","8vLQux71siMBOe9aKb1vWA==":"03.jpg","rUtXf1yld83XVVrwA6SSyA==":"mbr-640x853.jpg","TU7PlGkbQVltyNSFrEkWSQ==":"01.jpeg","0zVX33MxpOcuX/q1MQRvoA==":"02.jpeg","w4glllvRyLf0v6fhnNKjMg==":"03.jpeg","CtBQ29kIBWNKqC4qPxzfrw==":"04.jpeg","Jh+h3MYt8sId1GMi6BElMw==":"mbr-1920x1280.jpeg","dWKPLjwj0HbYU8IXIrsjKg==":"mbr-1920x1419.jpeg","S7sXvRFi/Hwkl/vERlBxmA==":"mbr-1-1920x1280.jpeg","6SdI1rgV75mteEwvhOjoaA==":"mbr-1920x1285.jpeg","u35aRJVnfSIuYFHMKZsc1Q==":"mbr-1920x1920.jpeg","9tkK8HkEp09XPZdVrmnILA==":"background2.jpeg","OHme0wnYDWRyWOgGoY1PKA==":"background2.jpg","Vq+9z78kxemykBm24sPbmQ==":"background2-1.jpeg","0rSlEqFgL+CMF6fFfTSl4Q==":"background2-2.jpeg"}